best_python/__init__.py
best_python/get_options.py
best_python/matlab_wrapper.py
best_python/solver.py
bestpython/__init__.py
bestpython/get_options.py
bestpython/matlab_wrapper.py
bestpython/mem_options.py
bestpython/solver.py
bestpython-0.0.5.dist-info/LICENSE
bestpython-0.0.5.dist-info/METADATA
bestpython-0.0.5.dist-info/WHEEL
bestpython-0.0.5.dist-info/top_level.txt
bestpython-0.0.5.dist-info/RECORD
