Metadata-Version: 2.1
Name: bestpython
Version: 0.0.5
Summary: A python wrapper for the MEM source method
Home-page: https://github.com/ilianAZZ/best-python
Author: MultiFunkIm Lab
Author-email: ilian@iazz.fr
License: UNKNOWN
Platform: UNKNOWN
Classifier: Programming Language :: Python :: 3
Classifier: Operating System :: OS Independent
Requires-Python: >=3.6
Requires-Dist: numpy >=1.26.4
Requires-Dist: mne >=1.6.1
Provides-Extra: matlab
